logger/__init__.py
logger/logger.py
logging_elk_manager-0.0.7.dist-info/LICENSE
logging_elk_manager-0.0.7.dist-info/METADATA
logging_elk_manager-0.0.7.dist-info/WHEEL
logging_elk_manager-0.0.7.dist-info/top_level.txt
logging_elk_manager-0.0.7.dist-info/RECORD
