Metadata-Version: 2.1
Name: logging-elk-manager
Version: 0.0.7
Summary: Facilitate the insertion of logs in our ELK.
Home-page: UNKNOWN
Author: Marco Aleixo
Author-email: marco.aleixo@misterturing.com
License: UNKNOWN
Keywords: logging,python,elk,elasticsearch
Platform: UNKNOWN
Classifier: Development Status :: 3 - Alpha
Classifier: Intended Audience :: Education
Classifier: Programming Language :: Python :: 2
Classifier: Programming Language :: Python :: 3
Classifier: Operating System :: MacOS :: MacOS X
Classifier: Operating System :: Microsoft :: Windows
Requires-Dist: pytz (==2020.5)
Requires-Dist: requests (==2.25.1)
